LICENSE
README.md
setup.py
first_package_leaf123.egg-info/PKG-INFO
first_package_leaf123.egg-info/SOURCES.txt
first_package_leaf123.egg-info/dependency_links.txt
first_package_leaf123.egg-info/top_level.txt
pkg/__init__.py
pkg/check_result.py