Metadata-Version: 2.1
Name: first-package-leaf123
Version: 0.0.1
Summary: My first package.
Home-page: https://github.com/me/myproject
Author: wei.hu
Author-email: 1223315226@qq.com
License: MIT
Classifier: License :: OSI Approved :: MIT License
Classifier: Programming Language :: Python
Classifier: Programming Language :: Python :: 3
Classifier: Programming Language :: Python :: 3.6
Classifier: Programming Language :: Python :: Implementation :: CPython
Classifier: Programming Language :: Python :: Implementation :: PyPy
Requires-Python: >=3.6.0
License-File: LICENSE
